-- BYTECODE -- init.lua:0-87
0001    GGET     0   0      ; "require"
0002    KSTR     1   1      ; "field.field"
0003    CALL     0   2   2
0004    GGET     1   0      ; "require"
0005    KSTR     2   2      ; "curses"
0006    CALL     1   2   2
0007    TNEW     2   3
0008    VARG     3   0   0
0009    TSETM    3   0      ; 1
0010    GGET     3   3      ; "math"
0011    TGETS    3   3   4  ; "randomseed"
0012    GGET     4   5      ; "os"
0013    TGETS    4   4   6  ; "clock"
0014    CALL     4   0   1
0015    CALLM    3   1   0
0016    KSHORT   3 115
0017    TGETS    4   1   7  ; "initscr"
0018    CALL     4   2   1
0019    MOV      6   4
0020    TGETS    5   4   8  ; "clear"
0021    CALL     5   1   2
0022    TGETS    5   1   9  ; "lines"
0023    CALL     5   2   1
0024    TGETS    6   1  10  ; "cols"
0025    CALL     6   2   1
0026    SUBVN    7   5   1  ; 3
0027    SUBVN    8   6   1  ; 3
0028    KSHORT   9 10000
0029    KSHORT  10 500
0030    DIVVN   11   9   2  ; 100
0031 => LOOP    12 => 0106
0032    TGETS   12   0  11  ; "new"
0033    MOV     13   7
0034    MOV     14   8
0035    MOV     15  10
0036    CALL    12   2   4
0037    KSHORT  13   0
0038 => LOOP    14 => 0105
0039    GGET    14   5      ; "os"
0040    TGETS   14  14   6  ; "clock"
0041    CALL    14   2   1
0042    MOV     16  12
0043    TGETS   15  12  12  ; "get_iteration"
0044    CALL    15   1   2
0045    ADDVN   13  13   3  ; 1
0046    MODVV   15  13  11
0047    SUBVN   16  13   3  ; 1
0048    MODVV   16  16  11
0049    ISGE    15  16
0050    JMP     15 => 0059
0051    GGET    15  13      ; "print"
0052    GGET    16   3      ; "math"
0053    TGETS   16  16  14  ; "floor"
0054    DIVVV   17  13  11
0055    CALL    16   2   2
0056    KSTR    17  15      ; " % done\r"
0057    CAT     16  16  17
0058    CALL    15   1   2
0059 => ISGE     9  13
0060    JMP     15 => 0092
0061    MOV     16  12
0062    TGETS   15  12  16  ; "to_print"
0063    CALL    15   2   2
0064    MOV     17   4
0065    TGETS   16   4   8  ; "clear"
0066    CALL    16   1   2
0067    KSHORT  16   1
0068    MOV     17   7
0069    KSHORT  18   1
0070    FORI    16 => 0081
0071 => MOV     21   4
0072    TGETS   20   4  17  ; "mvaddstr"
0073    MOV     22  19
0074    KSHORT  23   0
0075    TGETV   24  15  19
0076    KSTR    25  18      ; " "
0077    MOV     26  19
0078    CAT     24  24  26
0079    CALL    20   1   5
0080    FORL    16 => 0071
0081 => MOV     17   4
0082    TGETS   16   4  17  ; "mvaddstr"
0083    ADDVN   18   7   3  ; 1
0084    KSHORT  19   0
0085    KSTR    20  19      ; " iterations = "
0086    MOV     21  13
0087    CAT     20  20  21
0088    CALL    16   1   5
0089    MOV     17   4
0090    TGETS   16   4  20  ; "refresh"
0091    CALL    16   1   2
0092 => MOV     16  12
0093    TGETS   15  12  21  ; "count_bots"
0094    CALL    15   2   2
0095    ISNEN   15   4      ; 0
0096    JMP     15 => 0101
0097    GGET    15  13      ; "print"
0098    KSTR    16  22      ; "FAILED!!!\r"
0099    CALL    15   1   2
0100    JMP     14 => 0031
0101 => GGET    15   5      ; "os"
0102    TGETS   15  15   6  ; "clock"
0103    CALL    15   2   1
0104    JMP     14 => 0038
0105 => JMP     12 => 0031
0106 => RET0     0   1

